swarmpy/__init__.py
swarmpy/core.py
swarmpy/loader.py
swarmpy/strategies.py
swarmpython-1.0.2.dist-info/licenses/license.txt
swarmpython-1.0.2.dist-info/METADATA
swarmpython-1.0.2.dist-info/WHEEL
swarmpython-1.0.2.dist-info/top_level.txt
swarmpython-1.0.2.dist-info/RECORD
