Metadata-Version: 2.4
Name: swarmpython
Version: 1.0.2
Summary: A lightweight swarm intelligence framework for Python models
Author: Sai Vignesh Raj M, Gokulramanan V
License-Expression: MIT
Requires-Python: >=3.12
License-File: license.txt
Requires-Dist: numpy
Requires-Dist: scikit-learn
Requires-Dist: joblib
Dynamic: license-file
